sibyl_cli/__init__.py
sibyl_cli/auth.py
sibyl_cli/auth_store.py
sibyl_cli/client.py
sibyl_cli/common.py
sibyl_cli/config_cmd.py
sibyl_cli/config_store.py
sibyl_cli/context.py
sibyl_cli/crawl.py
sibyl_cli/document.py
sibyl_cli/entity.py
sibyl_cli/epic.py
sibyl_cli/explore.py
sibyl_cli/local.py
sibyl_cli/main.py
sibyl_cli/onboarding.py
sibyl_cli/org.py
sibyl_cli/project.py
sibyl_cli/source.py
sibyl_cli/state.py
sibyl_cli/task.py
sibyl_dev-0.2.3.dist-info/METADATA
sibyl_dev-0.2.3.dist-info/WHEEL
sibyl_dev-0.2.3.dist-info/entry_points.txt
sibyl_dev-0.2.3.dist-info/RECORD
