Metadata-Version: 2.4
Name: sibyl-dev
Version: 0.2.3
Summary: CLI for Sibyl - Collective Intelligence Runtime for AI agents
Project-URL: Homepage, https://github.com/hyperb1iss/sibyl
Project-URL: Repository, https://github.com/hyperb1iss/sibyl
Author-email: Stefanie Jane <stef@hyperbliss.tech>
License-Expression: Apache-2.0
Keywords: ai-agents,cli,knowledge-graph,mcp
Classifier: Development Status :: 3 - Alpha
Classifier: Environment :: Console
Classifier: Intended Audience :: Developers
Classifier: License :: OSI Approved :: Apache Software License
Classifier: Programming Language :: Python :: 3
Classifier: Programming Language :: Python :: 3.13
Classifier: Typing :: Typed
Requires-Python: >=3.13
Requires-Dist: httpx>=0.27
Requires-Dist: pyjwt>=2.10
Requires-Dist: pyyaml>=6.0
Requires-Dist: rich>=13.0
Requires-Dist: sibyl-core
Requires-Dist: tomli-w>=1.2.0
Requires-Dist: typer>=0.20.0
